boa_web/Browser.py
boa_web/Widgets.py
boa_web/__init__.py
boa_web/_utils.py
boa_web-0.0.5.dist-info/LICENSE
boa_web-0.0.5.dist-info/METADATA
boa_web-0.0.5.dist-info/WHEEL
boa_web-0.0.5.dist-info/top_level.txt
boa_web-0.0.5.dist-info/RECORD
