Metadata-Version: 2.1
Name: boa-web
Version: 0.0.5
Summary: boa_web is electron.js for python
Home-page: https://github.com/atharva-naik/boa_web
Author: Atharva Naik
Author-email: atharvanaik2018@gmail.com
License: MIT
Keywords: flask,electron,eel,cefpython,html,css,javascript
Platform: UNKNOWN
Classifier: License :: OSI Approved :: MIT License
Classifier: Programming Language :: Python :: 3
Classifier: Programming Language :: Python :: 3.7
Requires-Dist: bs4
Requires-Dist: tqdm
Requires-Dist: flask
Requires-Dist: jinja2
Requires-Dist: requests
Requires-Dist: ansicolors
Requires-Dist: cefpython3
